git_keeper_client-1.2.0.dist-info/licenses/LICENSE
gkeepclient/__init__.py
gkeepclient/assignment_uploader.py
gkeepclient/client_configuration.py
gkeepclient/client_function_decorators.py
gkeepclient/create_config.py
gkeepclient/duration_to_string.py
gkeepclient/fetch_submissions.py
gkeepclient/gkeep.py
gkeepclient/local_test.py
gkeepclient/new_assignment.py
gkeepclient/queries.py
gkeepclient/server_actions.py
gkeepclient/server_interface.py
gkeepclient/server_log_file_reader.py
gkeepclient/server_response_poller.py
gkeepclient/test_solution.py
gkeepclient/text_ui.py
gkeepclient/version.py
git_keeper_client-1.2.0.dist-info/METADATA
git_keeper_client-1.2.0.dist-info/WHEEL
git_keeper_client-1.2.0.dist-info/entry_points.txt
git_keeper_client-1.2.0.dist-info/top_level.txt
git_keeper_client-1.2.0.dist-info/RECORD
