Metadata-Version: 2.4
Name: git-keeper-client
Version: 1.2.0
Summary: A git-based system for distributing and collecting programming assignments with automatic feedback.
Home-page: https://github.com/git-keeper/git-keeper
Author: Nathan Sommer and Ben Coleman
Author-email: git-keeper@googlegroups.com
License: GPL 3
Classifier: Development Status :: 4 - Beta
Classifier: Intended Audience :: Education
Classifier: Environment :: Console
Classifier: Operating System :: OS Independent
Classifier: License :: OSI Approved :: GNU General Public License v3 (GPLv3)
Classifier: Programming Language :: Python
Classifier: Programming Language :: Python :: 3 :: Only
Classifier: Natural Language :: English
Classifier: Topic :: Education :: Testing
Classifier: Topic :: Education
License-File: LICENSE
Requires-Dist: git-keeper-core
Requires-Dist: paramiko
Requires-Dist: argcomplete
Dynamic: author
Dynamic: author-email
Dynamic: classifier
Dynamic: description
Dynamic: description-content-type
Dynamic: home-page
Dynamic: license
Dynamic: license-file
Dynamic: requires-dist
Dynamic: summary
